alnitak/__init__.py
alnitak/alnitak.conf
alnitak/certop.py
alnitak/classes.py
alnitak/config.py
alnitak/dane.py
alnitak/datafile.py
alnitak/datafile2.py
alnitak/datafile3.py
alnitak/exceptions.py
alnitak/logging.py
alnitak/main.py
alnitak/parser.py
alnitak/printrecord.py
alnitak/prog.py
alnitak/api/__init__.py
alnitak/api/binary.py
alnitak/api/cloudflare.py
alnitak/api/cloudflare4.py
alnitak/api/exec.py
alnitak/tests/__init__.py
alnitak/tests/call_test.py
alnitak/tests/cloudflare_test.py
alnitak/tests/config_test.py
alnitak/tests/main_test.py
alnitak/tests/parser_test.py
alnitak/tests/print_test.py
alnitak/tests/setup.py
tests/__init__.py
tests/config_test.py
tests/main_test.py
tests/setup.py
alnitak-0.2.2.dist-info/AUTHORS
alnitak-0.2.2.dist-info/LICENCE
alnitak-0.2.2.dist-info/METADATA
alnitak-0.2.2.dist-info/WHEEL
alnitak-0.2.2.dist-info/entry_points.txt
alnitak-0.2.2.dist-info/top_level.txt
alnitak-0.2.2.dist-info/RECORD
