Metadata-Version: 2.1
Name: alnitak
Version: 0.2.2
Summary: Create and manage DANE (DNS TLSA) records
Home-page: https://github.com/definitelyprobably/alnitak
Author: K. S. Kooner
Author-email: ksa.kooner@gmail.com
License: MIT
Keywords: dane tlsa
Platform: Linux
Platform: POSIX
Classifier: Development Status :: 4 - Beta
Classifier: Environment :: Console
Classifier: Programming Language :: Python :: 3
Classifier: Programming Language :: Python :: 3.4
Classifier: Programming Language :: Python :: 3.5
Classifier: Programming Language :: Python :: 3.6
Classifier: License :: OSI Approved :: MIT License
Classifier: Operating System :: POSIX :: Linux
Classifier: Intended Audience :: System Administrators
Classifier: Topic :: Internet
Classifier: Topic :: Security
Classifier: Topic :: System :: Systems Administration
Classifier: Topic :: Utilities
Requires-Dist: requests (>=2.21.0)
Requires-Dist: cryptography (>=2.4.2)
